[
	{
		"id" : 1,
		"unit_id" : 2258,
		"thoroughfare" : "7051 E OBELISKS ST",
		"locality" : "Boise",
		"administrative_area" : "ID",
		"postal_code" : "83716",
		"geocode" : "{\"latitude\": 43.531584, \"longitude\": -116.096276}",
		"inserted_at" : "2020-02-21 03:15:52",
		"updated_at" : "2020-02-21 03:15:52"
	},
	{
		"id" : 2,
		"unit_id" : 2259,
		"thoroughfare" : "7014 E FAREWELL BEND CT",
		"locality" : "Boise",
		"administrative_area" : "ID",
		"postal_code" : "83716",
		"geocode" : "{\"latitude\": 44.2982172, \"longitude\": -117.2190654}",
		"inserted_at" : "2020-02-21 03:20:11",
		"updated_at" : "2020-02-21 03:20:11"
	},
	{
		"id" : 10,
		"unit_id" : 2470,
		"thoroughfare" : "14718 Garner Falls Trail",
		"locality" : "Humble",
		"administrative_area" : "TX",
		"postal_code" : "77396",
		"geocode" : "{\"latitude\": 29.9311359, \"longitude\": -95.2684431}",
		"inserted_at" : "2020-03-26 13:21:40",
		"updated_at" : "2020-03-26 13:21:40"
	},
	{
		"id" : 11,
		"unit_id" : 2471,
		"thoroughfare" : "14706 Garner Falls Trail",
		"locality" : "Humble",
		"administrative_area" : "TX",
		"postal_code" : "77396",
		"geocode" : "{\"latitude\": 29.9311359, \"longitude\": -95.2684431}",
		"inserted_at" : "2020-03-26 13:47:52",
		"updated_at" : "2020-03-26 13:47:52"
	},
	{
		"id" : 216,
		"unit_id" : 2660,
		"thoroughfare" : "2569 Bayrose Cir",
		"locality" : "East Point",
		"administrative_area" : "GA",
		"postal_code" : "30344",
		"geocode" : "{\"latitude\": 33.7038853, \"longitude\": -84.4453324}",
		"inserted_at" : "2020-04-15 16:10:23",
		"updated_at" : "2020-04-15 16:10:23"
	},
	{
		"id" : 217,
		"unit_id" : 2661,
		"thoroughfare" : "2571 Bayrose Cir",
		"locality" : "East Point",
		"administrative_area" : "GA",
		"postal_code" : "30344",
		"geocode" : "{\"latitude\": 33.7038844, \"longitude\": -84.4453314}",
		"inserted_at" : "2020-04-15 16:11:10",
		"updated_at" : "2020-04-15 16:11:10"
	},
	{
		"id" : 218,
		"unit_id" : 2662,
		"thoroughfare" : "2464 Bayrose Cir",
		"locality" : "East Point",
		"administrative_area" : "GA",
		"postal_code" : "30344",
		"geocode" : "{\"latitude\": 33.7046232, \"longitude\": -84.44601159999999}",
		"inserted_at" : "2020-04-15 16:11:49",
		"updated_at" : "2020-04-15 16:11:49"
	},
	{
		"id" : 219,
		"unit_id" : 2663,
		"thoroughfare" : "2463 Bayrose Cir",
		"locality" : "East Point",
		"administrative_area" : "GA",
		"postal_code" : "30344",
		"geocode" : "{\"latitude\": 33.7039282, \"longitude\": -84.4453825}",
		"inserted_at" : "2020-04-15 16:12:33",
		"updated_at" : "2020-04-15 16:12:33"
	},
	{
		"id" : 220,
		"unit_id" : 2664,
		"thoroughfare" : "2462 Bayrose Cir",
		"locality" : "East Point",
		"administrative_area" : "GA",
		"postal_code" : "30344",
		"geocode" : "{\"latitude\": 33.7046232, \"longitude\": -84.44601159999999}",
		"inserted_at" : "2020-04-15 16:13:11",
		"updated_at" : "2020-04-15 16:13:11"
	},
	{
		"id" : 221,
		"unit_id" : 2665,
		"thoroughfare" : "2568 Bayrose Cir",
		"locality" : "East Point",
		"administrative_area" : "GA",
		"postal_code" : "30344",
		"geocode" : "{\"latitude\": 33.7046232, \"longitude\": -84.44601159999999}",
		"inserted_at" : "2020-04-15 16:13:48",
		"updated_at" : "2020-04-15 16:13:48"
	},
	{
		"id" : 222,
		"unit_id" : 2666,
		"thoroughfare" : "2465 Bayrose Cir",
		"locality" : "East Point",
		"administrative_area" : "GA",
		"postal_code" : "30344",
		"geocode" : "{\"latitude\": 33.7039274, \"longitude\": -84.44538159999999}",
		"inserted_at" : "2020-04-15 16:14:25",
		"updated_at" : "2020-04-15 16:14:25"
	},
	{
		"id" : 224,
		"unit_id" : 2667,
		"thoroughfare" : "2570 Bayrose Cir",
		"locality" : "East Point",
		"administrative_area" : "GA",
		"postal_code" : "30344",
		"geocode" : "{\"latitude\": 33.7046232, \"longitude\": -84.44601159999999}",
		"inserted_at" : "2020-04-15 16:18:33",
		"updated_at" : "2020-04-15 16:18:33"
	},
	{
		"id" : 225,
		"unit_id" : 2668,
		"thoroughfare" : "2784 Bayrose Cir",
		"locality" : "East Point",
		"administrative_area" : "GA",
		"postal_code" : "30344",
		"geocode" : "{\"latitude\": 33.7046232, \"longitude\": -84.44601159999999}",
		"inserted_at" : "2020-04-15 16:19:11",
		"updated_at" : "2020-04-15 16:19:11"
	},
	{
		"id" : 226,
		"unit_id" : 2669,
		"thoroughfare" : "2572 Bayrose Cir",
		"locality" : "East Point",
		"administrative_area" : "GA",
		"postal_code" : "30344",
		"geocode" : "{\"latitude\": 33.7046232, \"longitude\": -84.44601159999999}",
		"inserted_at" : "2020-04-15 16:20:04",
		"updated_at" : "2020-04-15 16:20:04"
	},
	{
		"id" : 227,
		"unit_id" : 2670,
		"thoroughfare" : "2786 Bayrose Cir",
		"locality" : "East Point",
		"administrative_area" : "GA",
		"postal_code" : "30344",
		"geocode" : "{\"latitude\": 33.7046232, \"longitude\": -84.44601159999999}",
		"inserted_at" : "2020-04-15 16:21:52",
		"updated_at" : "2020-04-15 16:21:52"
	},
	{
		"id" : 228,
		"unit_id" : 2671,
		"thoroughfare" : "2466 Bayrose Cir",
		"locality" : "East Point",
		"administrative_area" : "GA",
		"postal_code" : "30344",
		"geocode" : "{\"latitude\": 33.7046232, \"longitude\": -84.44601159999999}",
		"inserted_at" : "2020-04-15 16:22:33",
		"updated_at" : "2020-04-15 16:22:33"
	},
	{
		"id" : 229,
		"unit_id" : 2672,
		"thoroughfare" : "2781 Bayrose Cir",
		"locality" : "East Point",
		"administrative_area" : "GA",
		"postal_code" : "30344",
		"geocode" : "{\"latitude\": 33.7042141, \"longitude\": -84.4457163}",
		"inserted_at" : "2020-04-15 16:23:17",
		"updated_at" : "2020-04-15 16:23:17"
	},
	{
		"id" : 230,
		"unit_id" : 2673,
		"thoroughfare" : "2567 Bayrose Cir",
		"locality" : "East Point",
		"administrative_area" : "GA",
		"postal_code" : "30344",
		"geocode" : "{\"latitude\": 33.7038861, \"longitude\": -84.4453333}",
		"inserted_at" : "2020-04-15 16:24:11",
		"updated_at" : "2020-04-15 16:24:11"
	},
	{
		"id" : 231,
		"unit_id" : 2674,
		"thoroughfare" : "2461 Bayrose Cir",
		"locality" : "East Point",
		"administrative_area" : "GA",
		"postal_code" : "30344",
		"geocode" : "{\"latitude\": 33.703929, \"longitude\": -84.44538349999999}",
		"inserted_at" : "2020-04-15 16:27:29",
		"updated_at" : "2020-04-15 16:27:29"
	},
	{
		"id" : 232,
		"unit_id" : 2675,
		"thoroughfare" : "2008 Bayrose Cir",
		"locality" : "East Point",
		"administrative_area" : "GA",
		"postal_code" : "30344",
		"geocode" : "{\"latitude\": 33.7046232, \"longitude\": -84.44601159999999}",
		"inserted_at" : "2020-04-15 16:28:12",
		"updated_at" : "2020-04-15 16:28:12"
	},
	{
		"id" : 233,
		"unit_id" : 2676,
		"thoroughfare" : "2011 Bayrose Cir",
		"locality" : "East Point",
		"administrative_area" : "GA",
		"postal_code" : "30344",
		"geocode" : "{\"latitude\": 33.7041113, \"longitude\": -84.44559629999999}",
		"inserted_at" : "2020-04-15 16:28:48",
		"updated_at" : "2020-04-15 16:28:48"
	},
	{
		"id" : 235,
		"unit_id" : 2678,
		"thoroughfare" : "2010 Bayrose Cir",
		"locality" : "East Point",
		"administrative_area" : "GA",
		"postal_code" : "30344",
		"geocode" : "{\"latitude\": 33.7046232, \"longitude\": -84.44601159999999}",
		"inserted_at" : "2020-04-15 16:30:19",
		"updated_at" : "2020-04-15 16:30:19"
	},
	{
		"id" : 236,
		"unit_id" : 2679,
		"thoroughfare" : "2012 Bayrose Cir",
		"locality" : "East Point",
		"administrative_area" : "GA",
		"postal_code" : "30344",
		"geocode" : "{\"latitude\": 33.7046232, \"longitude\": -84.44601159999999}",
		"inserted_at" : "2020-04-15 16:31:02",
		"updated_at" : "2020-04-15 16:31:02"
	},
	{
		"id" : 237,
		"unit_id" : 2680,
		"thoroughfare" : "2007 Bayrose Cir",
		"locality" : "East Point",
		"administrative_area" : "GA",
		"postal_code" : "30344",
		"geocode" : "{\"latitude\": 33.7041129, \"longitude\": -84.44559819999999}",
		"inserted_at" : "2020-04-15 16:31:44",
		"updated_at" : "2020-04-15 16:31:44"
	},
	{
		"id" : 240,
		"unit_id" : 2568,
		"thoroughfare" : "81 Thompson St, unit 102",
		"locality" : "Alpharetta",
		"administrative_area" : "GA",
		"postal_code" : "30009",
		"geocode" : "{\"latitude\": 34.071826, \"longitude\": -84.2909947}",
		"inserted_at" : "2020-04-16 02:03:42",
		"updated_at" : "2020-04-16 02:03:42"
	},
	{
		"id" : 241,
		"unit_id" : 2566,
		"thoroughfare" : "81 Thompson St, unit 201",
		"locality" : "Alpharetta",
		"administrative_area" : "GA",
		"postal_code" : "30009",
		"geocode" : "{\"latitude\": 34.071826, \"longitude\": -84.2909947}",
		"inserted_at" : "2020-04-16 02:03:59",
		"updated_at" : "2020-04-16 02:03:59"
	},
	{
		"id" : 245,
		"unit_id" : 2677,
		"thoroughfare" : "2009 Bayrose Cir",
		"locality" : "East Point",
		"administrative_area" : "GA",
		"postal_code" : "30344",
		"geocode" : "{\"latitude\": 33.7041121, \"longitude\": -84.4455972}",
		"inserted_at" : "2020-04-27 16:53:09",
		"updated_at" : "2020-04-27 16:53:09"
	},
	{
		"id" : 246,
		"unit_id" : 2453,
		"thoroughfare" : "71 Thompson Street, Unit 202",
		"locality" : "Alpharetta",
		"administrative_area" : "GA",
		"postal_code" : "30009",
		"geocode" : "{\"latitude\": 34.0718039, \"longitude\": -84.29130119999999}",
		"inserted_at" : "2020-04-29 16:40:02",
		"updated_at" : "2020-04-29 16:40:02"
	},
	{
		"id" : 247,
		"unit_id" : 2700,
		"thoroughfare" : "15 Hudson Yards",
		"locality" : "New York",
		"administrative_area" : "NY",
		"postal_code" : "10001",
		"geocode" : "{\"latitude\": 40.7535725, \"longitude\": -74.0025845}",
		"inserted_at" : "2020-04-30 19:58:16",
		"updated_at" : "2020-04-30 19:58:16"
	},
	{
		"id" : 248,
		"unit_id" : 2701,
		"thoroughfare" : "15 Hudson Yards ",
		"locality" : "New York",
		"administrative_area" : "NY",
		"postal_code" : "10001",
		"geocode" : "{\"latitude\": 40.7535725, \"longitude\": -74.0025845}",
		"inserted_at" : "2020-04-30 20:16:15",
		"updated_at" : "2020-04-30 20:16:15"
	},
	{
		"id" : 249,
		"unit_id" : 2702,
		"thoroughfare" : "15 Hudson Yards",
		"locality" : "New York",
		"administrative_area" : "NY",
		"postal_code" : "10001",
		"geocode" : "{\"latitude\": 40.7535725, \"longitude\": -74.0025845}",
		"inserted_at" : "2020-04-30 20:17:21",
		"updated_at" : "2020-04-30 20:17:21"
	},
	{
		"id" : 250,
		"unit_id" : 2703,
		"thoroughfare" : "15 Hudson Yards",
		"locality" : "New York",
		"administrative_area" : "NY",
		"postal_code" : "10001",
		"geocode" : "{\"latitude\": 40.7535725, \"longitude\": -74.0025845}",
		"inserted_at" : "2020-04-30 20:18:26",
		"updated_at" : "2020-04-30 20:18:26"
	},
	{
		"id" : 251,
		"unit_id" : 2704,
		"thoroughfare" : "15 Hudson Yards",
		"locality" : "New York",
		"administrative_area" : "NY",
		"postal_code" : "10001",
		"geocode" : "{\"latitude\": 40.7535725, \"longitude\": -74.0025845}",
		"inserted_at" : "2020-04-30 20:19:12",
		"updated_at" : "2020-04-30 20:19:12"
	},
	{
		"id" : 252,
		"unit_id" : 2705,
		"thoroughfare" : "15 Hudson Yards",
		"locality" : "New York",
		"administrative_area" : "NY",
		"postal_code" : "10001",
		"geocode" : "{\"latitude\": 40.7535725, \"longitude\": -74.0025845}",
		"inserted_at" : "2020-04-30 20:20:22",
		"updated_at" : "2020-04-30 20:20:22"
	},
	{
		"id" : 253,
		"unit_id" : 2706,
		"thoroughfare" : "15 Hudson Yards",
		"locality" : "New York",
		"administrative_area" : "NY",
		"postal_code" : "10001",
		"geocode" : "{\"latitude\": 40.7535725, \"longitude\": -74.0025845}",
		"inserted_at" : "2020-04-30 20:21:43",
		"updated_at" : "2020-04-30 20:21:43"
	},
	{
		"id" : 254,
		"unit_id" : 2707,
		"thoroughfare" : "15 Hudson Yards",
		"locality" : "New York",
		"administrative_area" : "NY",
		"postal_code" : "10001",
		"geocode" : "{\"latitude\": 40.7535725, \"longitude\": -74.0025845}",
		"inserted_at" : "2020-04-30 20:22:55",
		"updated_at" : "2020-04-30 20:22:55"
	},
	{
		"id" : 257,
		"unit_id" : 2708,
		"thoroughfare" : "35 Hudson Yards",
		"locality" : "New York",
		"administrative_area" : "NY",
		"postal_code" : "10001",
		"geocode" : "{\"latitude\": 40.7546241, \"longitude\": -74.0023133}",
		"inserted_at" : "2020-04-30 20:43:21",
		"updated_at" : "2020-04-30 20:43:21"
	},
	{
		"id" : 258,
		"unit_id" : 2709,
		"thoroughfare" : "35 Hudson Yards",
		"locality" : "New York",
		"administrative_area" : "NY",
		"postal_code" : "10001",
		"geocode" : "{\"latitude\": 40.7546241, \"longitude\": -74.0023133}",
		"inserted_at" : "2020-04-30 20:44:03",
		"updated_at" : "2020-04-30 20:44:03"
	},
	{
		"id" : 259,
		"unit_id" : 2710,
		"thoroughfare" : "35 Hudson Yards",
		"locality" : "New York",
		"administrative_area" : "NY",
		"postal_code" : "10001",
		"geocode" : "{\"latitude\": 40.7546241, \"longitude\": -74.0023133}",
		"inserted_at" : "2020-04-30 20:45:21",
		"updated_at" : "2020-04-30 20:45:21"
	},
	{
		"id" : 261,
		"unit_id" : 2711,
		"thoroughfare" : "35 Hudson Yards",
		"locality" : "New York",
		"administrative_area" : "NY",
		"postal_code" : "10001",
		"geocode" : "{\"latitude\": 40.7546241, \"longitude\": -74.0023133}",
		"inserted_at" : "2020-04-30 20:47:18",
		"updated_at" : "2020-04-30 20:47:18"
	},
	{
		"id" : 262,
		"unit_id" : 2712,
		"thoroughfare" : "35 Hudson Yards",
		"locality" : "New York",
		"administrative_area" : "NY",
		"postal_code" : "10001",
		"geocode" : "{\"latitude\": 40.7546241, \"longitude\": -74.0023133}",
		"inserted_at" : "2020-04-30 20:48:08",
		"updated_at" : "2020-04-30 20:48:08"
	},
	{
		"id" : 263,
		"unit_id" : 2713,
		"thoroughfare" : "35 Hudson Yards",
		"locality" : "New York",
		"administrative_area" : "NY",
		"postal_code" : "10001",
		"geocode" : "{\"latitude\": 40.7546241, \"longitude\": -74.0023133}",
		"inserted_at" : "2020-04-30 20:49:02",
		"updated_at" : "2020-04-30 20:49:02"
	},
	{
		"id" : 265,
		"unit_id" : 2565,
		"thoroughfare" : "81 Thompson St, unit 101",
		"locality" : "Alpharetta",
		"administrative_area" : "GA",
		"postal_code" : "30009",
		"geocode" : "{\"latitude\": 34.071826, \"longitude\": -84.2909947}",
		"inserted_at" : "2020-05-14 14:27:35",
		"updated_at" : "2020-05-14 14:27:35"
	},
	{
		"id" : 277,
		"unit_id" : 2640,
		"thoroughfare" : "410 Rhode Island Ave NE",
		"locality" : "Washington",
		"administrative_area" : "DC",
		"postal_code" : "20002",
		"geocode" : "{\"latitude\": 38.9202328, \"longitude\": -76.9999917}",
		"inserted_at" : "2020-05-21 12:19:59",
		"updated_at" : "2020-05-21 12:19:59"
	},
	{
		"id" : 278,
		"unit_id" : 2642,
		"thoroughfare" : "410 Rhode Island Ave NE",
		"locality" : "Washington",
		"administrative_area" : "DC",
		"postal_code" : "20002",
		"geocode" : "{\"latitude\": 38.9202328, \"longitude\": -76.9999917}",
		"inserted_at" : "2020-05-21 12:20:18",
		"updated_at" : "2020-05-21 12:20:18"
	},
	{
		"id" : 279,
		"unit_id" : 2639,
		"thoroughfare" : "410 Rhode Island Ave NE",
		"locality" : "Washington",
		"administrative_area" : "DC",
		"postal_code" : "20002",
		"geocode" : "{\"latitude\": 38.9202328, \"longitude\": -76.9999917}",
		"inserted_at" : "2020-05-21 12:20:36",
		"updated_at" : "2020-05-21 12:20:36"
	},
	{
		"id" : 280,
		"unit_id" : 2641,
		"thoroughfare" : "410 Rhode Island Ave NE",
		"locality" : "Washington",
		"administrative_area" : "DC",
		"postal_code" : "20002",
		"geocode" : "{\"latitude\": 38.9202328, \"longitude\": -76.9999917}",
		"inserted_at" : "2020-05-21 12:20:52",
		"updated_at" : "2020-05-21 12:20:52"
	},
	{
		"id" : 281,
		"unit_id" : 2643,
		"thoroughfare" : "410 Rhode Island Ave NE",
		"locality" : "Washington",
		"administrative_area" : "DC",
		"postal_code" : "20002",
		"geocode" : "{\"latitude\": 38.9202328, \"longitude\": -76.9999917}",
		"inserted_at" : "2020-05-21 12:21:10",
		"updated_at" : "2020-05-21 12:21:10"
	},
	{
		"id" : 288,
		"unit_id" : 2582,
		"thoroughfare" : "410 Rhode Island Ave NE",
		"locality" : "Washington",
		"administrative_area" : "DC",
		"postal_code" : "20002",
		"geocode" : "{\"latitude\": 38.9202328, \"longitude\": -76.9999917}",
		"inserted_at" : "2020-05-22 15:13:04",
		"updated_at" : "2020-05-22 15:13:04"
	},
	{
		"id" : 289,
		"unit_id" : 2580,
		"thoroughfare" : "410 Rhode Island Ave NE",
		"locality" : "Washington",
		"administrative_area" : "DC",
		"postal_code" : "20002",
		"geocode" : "{\"latitude\": 38.9202328, \"longitude\": -76.9999917}",
		"inserted_at" : "2020-05-22 15:15:35",
		"updated_at" : "2020-05-22 15:15:35"
	},
	{
		"id" : 290,
		"unit_id" : 2589,
		"thoroughfare" : "410 Rhode Island Ave NE",
		"locality" : "Washington",
		"administrative_area" : "DC",
		"postal_code" : "20002",
		"geocode" : "{\"latitude\": 38.9202328, \"longitude\": -76.9999917}",
		"inserted_at" : "2020-05-22 15:16:22",
		"updated_at" : "2020-05-22 15:16:22"
	},
	{
		"id" : 291,
		"unit_id" : 2594,
		"thoroughfare" : "410 Rhode Island Ave NE",
		"locality" : "Washington",
		"administrative_area" : "DC",
		"postal_code" : "20002",
		"geocode" : "{\"latitude\": 38.9202328, \"longitude\": -76.9999917}",
		"inserted_at" : "2020-05-22 15:17:16",
		"updated_at" : "2020-05-22 15:17:16"
	},
	{
		"id" : 292,
		"unit_id" : 2617,
		"thoroughfare" : "410 Rhode Island Ave NE",
		"locality" : "Washington",
		"administrative_area" : "DC",
		"postal_code" : "20002",
		"geocode" : "{\"latitude\": 38.9202328, \"longitude\": -76.9999917}",
		"inserted_at" : "2020-05-22 15:18:02",
		"updated_at" : "2020-05-22 15:18:02"
	},
	{
		"id" : 293,
		"unit_id" : 2625,
		"thoroughfare" : "410 Rhode Island Ave NE",
		"locality" : "Washington",
		"administrative_area" : "DC",
		"postal_code" : "20002",
		"geocode" : "{\"latitude\": 38.9202328, \"longitude\": -76.9999917}",
		"inserted_at" : "2020-05-22 15:20:22",
		"updated_at" : "2020-05-22 15:20:22"
	},
	{
		"id" : 294,
		"unit_id" : 2599,
		"thoroughfare" : "410 Rhode Island Ave NE",
		"locality" : "Washington",
		"administrative_area" : "DC",
		"postal_code" : "20002",
		"geocode" : "{\"latitude\": 38.9202328, \"longitude\": -76.9999917}",
		"inserted_at" : "2020-05-22 15:21:31",
		"updated_at" : "2020-05-22 15:21:31"
	},
	{
		"id" : 295,
		"unit_id" : 2604,
		"thoroughfare" : "410 Rhode Island Ave NE",
		"locality" : "Washington",
		"administrative_area" : "DC",
		"postal_code" : "20002",
		"geocode" : "{\"latitude\": 38.9202328, \"longitude\": -76.9999917}",
		"inserted_at" : "2020-05-22 15:22:13",
		"updated_at" : "2020-05-22 15:22:13"
	},
	{
		"id" : 296,
		"unit_id" : 2630,
		"thoroughfare" : "410 Rhode Island Ave NE",
		"locality" : "Washington",
		"administrative_area" : "DC",
		"postal_code" : "20002",
		"geocode" : "{\"latitude\": 38.9202328, \"longitude\": -76.9999917}",
		"inserted_at" : "2020-05-22 15:22:54",
		"updated_at" : "2020-05-22 15:22:54"
	},
	{
		"id" : 297,
		"unit_id" : 2610,
		"thoroughfare" : "410 Rhode Island Ave NE",
		"locality" : "Washington",
		"administrative_area" : "DC",
		"postal_code" : "20002",
		"geocode" : "{\"latitude\": 38.9202328, \"longitude\": -76.9999917}",
		"inserted_at" : "2020-05-22 15:24:20",
		"updated_at" : "2020-05-22 15:24:20"
	},
	{
		"id" : 298,
		"unit_id" : 2579,
		"thoroughfare" : "410 Rhode Island Ave NE",
		"locality" : "Washington",
		"administrative_area" : "DC",
		"postal_code" : "20002",
		"geocode" : "{\"latitude\": 38.9202328, \"longitude\": -76.9999917}",
		"inserted_at" : "2020-05-22 15:29:15",
		"updated_at" : "2020-05-22 15:29:15"
	},
	{
		"id" : 299,
		"unit_id" : 2581,
		"thoroughfare" : "410 Rhode Island Ave NE",
		"locality" : "Washington",
		"administrative_area" : "DC",
		"postal_code" : "20002",
		"geocode" : "{\"latitude\": 38.9202328, \"longitude\": -76.9999917}",
		"inserted_at" : "2020-05-22 15:29:56",
		"updated_at" : "2020-05-22 15:29:56"
	},
	{
		"id" : 300,
		"unit_id" : 2590,
		"thoroughfare" : "410 Rhode Island Ave NE",
		"locality" : "Washington",
		"administrative_area" : "DC",
		"postal_code" : "20002",
		"geocode" : "{\"latitude\": 38.9202328, \"longitude\": -76.9999917}",
		"inserted_at" : "2020-05-22 15:30:40",
		"updated_at" : "2020-05-22 15:30:40"
	},
	{
		"id" : 301,
		"unit_id" : 2595,
		"thoroughfare" : "410 Rhode Island Ave NE",
		"locality" : "Washington",
		"administrative_area" : "DC",
		"postal_code" : "20002",
		"geocode" : "{\"latitude\": 38.9202328, \"longitude\": -76.9999917}",
		"inserted_at" : "2020-05-22 15:31:23",
		"updated_at" : "2020-05-22 15:31:23"
	},
	{
		"id" : 302,
		"unit_id" : 2618,
		"thoroughfare" : "410 Rhode Island Ave NE",
		"locality" : "Washington",
		"administrative_area" : "DC",
		"postal_code" : "20002",
		"geocode" : "{\"latitude\": 38.9202328, \"longitude\": -76.9999917}",
		"inserted_at" : "2020-05-22 15:32:00",
		"updated_at" : "2020-05-22 15:32:00"
	},
	{
		"id" : 303,
		"unit_id" : 2571,
		"thoroughfare" : "410 Rhode Island Ave NE",
		"locality" : "Washington",
		"administrative_area" : "DC",
		"postal_code" : "20002",
		"geocode" : "{\"latitude\": 38.9202328, \"longitude\": -76.9999917}",
		"inserted_at" : "2020-05-22 15:33:41",
		"updated_at" : "2020-05-22 15:33:41"
	},
	{
		"id" : 304,
		"unit_id" : 2626,
		"thoroughfare" : "410 Rhode Island Ave NE",
		"locality" : "Washington",
		"administrative_area" : "DC",
		"postal_code" : "20002",
		"geocode" : "{\"latitude\": 38.9202328, \"longitude\": -76.9999917}",
		"inserted_at" : "2020-05-22 15:34:55",
		"updated_at" : "2020-05-22 15:34:55"
	},
	{
		"id" : 306,
		"unit_id" : 2605,
		"thoroughfare" : "410 Rhode Island Ave NE",
		"locality" : "Washington",
		"administrative_area" : "DC",
		"postal_code" : "20002",
		"geocode" : "{\"latitude\": 38.9202328, \"longitude\": -76.9999917}",
		"inserted_at" : "2020-05-22 15:36:16",
		"updated_at" : "2020-05-22 15:36:16"
	},
	{
		"id" : 307,
		"unit_id" : 2631,
		"thoroughfare" : "410 Rhode Island Ave NE",
		"locality" : "Washington",
		"administrative_area" : "DC",
		"postal_code" : "20002",
		"geocode" : "{\"latitude\": 38.9202328, \"longitude\": -76.9999917}",
		"inserted_at" : "2020-05-22 15:37:24",
		"updated_at" : "2020-05-22 15:37:24"
	},
	{
		"id" : 309,
		"unit_id" : 2611,
		"thoroughfare" : "410 Rhode Island Ave NE",
		"locality" : "Washington",
		"administrative_area" : "DC",
		"postal_code" : "20002",
		"geocode" : "{\"latitude\": 38.9202328, \"longitude\": -76.9999917}",
		"inserted_at" : "2020-05-22 15:38:43",
		"updated_at" : "2020-05-22 15:38:43"
	},
	{
		"id" : 310,
		"unit_id" : 2622,
		"thoroughfare" : "410 Rhode Island Ave NE",
		"locality" : "Washington",
		"administrative_area" : "DC",
		"postal_code" : "20002",
		"geocode" : "{\"latitude\": 38.9202328, \"longitude\": -76.9999917}",
		"inserted_at" : "2020-05-22 15:39:27",
		"updated_at" : "2020-05-22 15:39:27"
	},
	{
		"id" : 311,
		"unit_id" : 2583,
		"thoroughfare" : "410 Rhode Island Ave NE",
		"locality" : "Washington",
		"administrative_area" : "DC",
		"postal_code" : "20002",
		"geocode" : "{\"latitude\": 38.9202328, \"longitude\": -76.9999917}",
		"inserted_at" : "2020-05-22 15:40:02",
		"updated_at" : "2020-05-22 15:40:02"
	},
	{
		"id" : 312,
		"unit_id" : 2586,
		"thoroughfare" : "410 Rhode Island Ave NE",
		"locality" : "Washington",
		"administrative_area" : "DC",
		"postal_code" : "20002",
		"geocode" : "{\"latitude\": 38.9202328, \"longitude\": -76.9999917}",
		"inserted_at" : "2020-05-22 15:40:40",
		"updated_at" : "2020-05-22 15:40:40"
	},
	{
		"id" : 313,
		"unit_id" : 2591,
		"thoroughfare" : "410 Rhode Island Ave NE",
		"locality" : "Washington",
		"administrative_area" : "DC",
		"postal_code" : "20002",
		"geocode" : "{\"latitude\": 38.9202328, \"longitude\": -76.9999917}",
		"inserted_at" : "2020-05-22 15:41:02",
		"updated_at" : "2020-05-22 15:41:02"
	},
	{
		"id" : 314,
		"unit_id" : 2596,
		"thoroughfare" : "410 Rhode Island Ave NE",
		"locality" : "Washington",
		"administrative_area" : "DC",
		"postal_code" : "20002",
		"geocode" : "{\"latitude\": 38.9202328, \"longitude\": -76.9999917}",
		"inserted_at" : "2020-05-22 15:41:25",
		"updated_at" : "2020-05-22 15:41:25"
	},
	{
		"id" : 315,
		"unit_id" : 2619,
		"thoroughfare" : "410 Rhode Island Ave NE",
		"locality" : "Washington",
		"administrative_area" : "DC",
		"postal_code" : "20002",
		"geocode" : "{\"latitude\": 38.9202328, \"longitude\": -76.9999917}",
		"inserted_at" : "2020-05-22 15:42:03",
		"updated_at" : "2020-05-22 15:42:03"
	},
	{
		"id" : 316,
		"unit_id" : 2614,
		"thoroughfare" : "410 Rhode Island Ave NE",
		"locality" : "Washington",
		"administrative_area" : "DC",
		"postal_code" : "20002",
		"geocode" : "{\"latitude\": 38.9202328, \"longitude\": -76.9999917}",
		"inserted_at" : "2020-05-22 15:42:34",
		"updated_at" : "2020-05-22 15:42:34"
	},
	{
		"id" : 317,
		"unit_id" : 2572,
		"thoroughfare" : "410 Rhode Island Ave NE",
		"locality" : "Washington",
		"administrative_area" : "DC",
		"postal_code" : "20002",
		"geocode" : "{\"latitude\": 38.9202328, \"longitude\": -76.9999917}",
		"inserted_at" : "2020-05-22 15:43:22",
		"updated_at" : "2020-05-22 15:43:22"
	},
	{
		"id" : 318,
		"unit_id" : 2627,
		"thoroughfare" : "410 Rhode Island Ave NE",
		"locality" : "Washington",
		"administrative_area" : "DC",
		"postal_code" : "20002",
		"geocode" : "{\"latitude\": 38.9202328, \"longitude\": -76.9999917}",
		"inserted_at" : "2020-05-22 15:44:00",
		"updated_at" : "2020-05-22 15:44:00"
	},
	{
		"id" : 321,
		"unit_id" : 2600,
		"thoroughfare" : "410 Rhode Island Ave NE",
		"locality" : "Washington",
		"administrative_area" : "DC",
		"postal_code" : "20002",
		"geocode" : "{\"latitude\": 38.9202328, \"longitude\": -76.9999917}",
		"inserted_at" : "2020-05-22 15:45:55",
		"updated_at" : "2020-05-22 15:45:55"
	},
	{
		"id" : 322,
		"unit_id" : 2601,
		"thoroughfare" : "410 Rhode Island Ave NE",
		"locality" : "Washington",
		"administrative_area" : "DC",
		"postal_code" : "20002",
		"geocode" : "{\"latitude\": 38.9202328, \"longitude\": -76.9999917}",
		"inserted_at" : "2020-05-22 15:46:47",
		"updated_at" : "2020-05-22 15:46:47"
	},
	{
		"id" : 323,
		"unit_id" : 2606,
		"thoroughfare" : "410 Rhode Island Ave NE",
		"locality" : "Washington",
		"administrative_area" : "DC",
		"postal_code" : "20002",
		"geocode" : "{\"latitude\": 38.9202328, \"longitude\": -76.9999917}",
		"inserted_at" : "2020-05-22 15:47:28",
		"updated_at" : "2020-05-22 15:47:28"
	},
	{
		"id" : 324,
		"unit_id" : 2632,
		"thoroughfare" : "410 Rhode Island Ave NE",
		"locality" : "Washington",
		"administrative_area" : "DC",
		"postal_code" : "20002",
		"geocode" : "{\"latitude\": 38.9202328, \"longitude\": -76.9999917}",
		"inserted_at" : "2020-05-22 15:48:10",
		"updated_at" : "2020-05-22 15:48:10"
	},
	{
		"id" : 325,
		"unit_id" : 2576,
		"thoroughfare" : "410 Rhode Island Ave NE",
		"locality" : "Washington",
		"administrative_area" : "DC",
		"postal_code" : "20002",
		"geocode" : "{\"latitude\": 38.9202328, \"longitude\": -76.9999917}",
		"inserted_at" : "2020-05-22 15:48:43",
		"updated_at" : "2020-05-22 15:48:43"
	},
	{
		"id" : 326,
		"unit_id" : 2612,
		"thoroughfare" : "410 Rhode Island Ave NE",
		"locality" : "Washington",
		"administrative_area" : "DC",
		"postal_code" : "20002",
		"geocode" : "{\"latitude\": 38.9202328, \"longitude\": -76.9999917}",
		"inserted_at" : "2020-05-22 15:49:26",
		"updated_at" : "2020-05-22 15:49:26"
	},
	{
		"id" : 327,
		"unit_id" : 2623,
		"thoroughfare" : "410 Rhode Island Ave NE",
		"locality" : "Washington",
		"administrative_area" : "DC",
		"postal_code" : "20002",
		"geocode" : "{\"latitude\": 38.9202328, \"longitude\": -76.9999917}",
		"inserted_at" : "2020-05-22 15:50:02",
		"updated_at" : "2020-05-22 15:50:02"
	},
	{
		"id" : 328,
		"unit_id" : 2584,
		"thoroughfare" : "410 Rhode Island Ave NE",
		"locality" : "Washington",
		"administrative_area" : "DC",
		"postal_code" : "20002",
		"geocode" : "{\"latitude\": 38.9202328, \"longitude\": -76.9999917}",
		"inserted_at" : "2020-05-22 15:50:59",
		"updated_at" : "2020-05-22 15:50:59"
	},
	{
		"id" : 329,
		"unit_id" : 2587,
		"thoroughfare" : "410 Rhode Island Ave NE",
		"locality" : "Washington",
		"administrative_area" : "DC",
		"postal_code" : "20002",
		"geocode" : "{\"latitude\": 38.9202328, \"longitude\": -76.9999917}",
		"inserted_at" : "2020-05-22 15:51:59",
		"updated_at" : "2020-05-22 15:51:59"
	},
	{
		"id" : 330,
		"unit_id" : 2592,
		"thoroughfare" : "410 Rhode Island Ave NE",
		"locality" : "Washington",
		"administrative_area" : "DC",
		"postal_code" : "20002",
		"geocode" : "{\"latitude\": 38.9202328, \"longitude\": -76.9999917}",
		"inserted_at" : "2020-05-22 16:12:33",
		"updated_at" : "2020-05-22 16:12:33"
	},
	{
		"id" : 331,
		"unit_id" : 2597,
		"thoroughfare" : "410 Rhode Island Ave NE",
		"locality" : "Washington",
		"administrative_area" : "DC",
		"postal_code" : "20002",
		"geocode" : "{\"latitude\": 38.9202328, \"longitude\": -76.9999917}",
		"inserted_at" : "2020-05-22 16:12:55",
		"updated_at" : "2020-05-22 16:12:55"
	},
	{
		"id" : 332,
		"unit_id" : 2620,
		"thoroughfare" : "410 Rhode Island Ave NE",
		"locality" : "Washington",
		"administrative_area" : "DC",
		"postal_code" : "20002",
		"geocode" : "{\"latitude\": 38.9202328, \"longitude\": -76.9999917}",
		"inserted_at" : "2020-05-22 16:13:28",
		"updated_at" : "2020-05-22 16:13:28"
	},
	{
		"id" : 333,
		"unit_id" : 2615,
		"thoroughfare" : "410 Rhode Island Ave NE",
		"locality" : "Washington",
		"administrative_area" : "DC",
		"postal_code" : "20002",
		"geocode" : "{\"latitude\": 38.9202328, \"longitude\": -76.9999917}",
		"inserted_at" : "2020-05-22 16:14:31",
		"updated_at" : "2020-05-22 16:14:31"
	},
	{
		"id" : 334,
		"unit_id" : 2573,
		"thoroughfare" : "410 Rhode Island Ave NE",
		"locality" : "Washington",
		"administrative_area" : "DC",
		"postal_code" : "20002",
		"geocode" : "{\"latitude\": 38.9202328, \"longitude\": -76.9999917}",
		"inserted_at" : "2020-05-22 16:15:05",
		"updated_at" : "2020-05-22 16:15:05"
	},
	{
		"id" : 335,
		"unit_id" : 2628,
		"thoroughfare" : "410 Rhode Island Ave NE",
		"locality" : "Washington",
		"administrative_area" : "DC",
		"postal_code" : "20002",
		"geocode" : "{\"latitude\": 38.9202328, \"longitude\": -76.9999917}",
		"inserted_at" : "2020-05-22 16:15:37",
		"updated_at" : "2020-05-22 16:15:37"
	},
	{
		"id" : 336,
		"unit_id" : 2602,
		"thoroughfare" : "410 Rhode Island Ave NE",
		"locality" : "Washington",
		"administrative_area" : "DC",
		"postal_code" : "20002",
		"geocode" : "{\"latitude\": 38.9202328, \"longitude\": -76.9999917}",
		"inserted_at" : "2020-05-22 16:16:24",
		"updated_at" : "2020-05-22 16:16:24"
	},
	{
		"id" : 338,
		"unit_id" : 2607,
		"thoroughfare" : "410 Rhode Island Ave NE",
		"locality" : "Washington",
		"administrative_area" : "DC",
		"postal_code" : "20002",
		"geocode" : "{\"latitude\": 38.9202328, \"longitude\": -76.9999917}",
		"inserted_at" : "2020-05-22 16:17:11",
		"updated_at" : "2020-05-22 16:17:11"
	},
	{
		"id" : 339,
		"unit_id" : 2633,
		"thoroughfare" : "410 Rhode Island Ave NE",
		"locality" : "Washington",
		"administrative_area" : "DC",
		"postal_code" : "20002",
		"geocode" : "{\"latitude\": 38.9202328, \"longitude\": -76.9999917}",
		"inserted_at" : "2020-05-22 16:17:45",
		"updated_at" : "2020-05-22 16:17:45"
	},
	{
		"id" : 340,
		"unit_id" : 2577,
		"thoroughfare" : "410 Rhode Island Ave NE",
		"locality" : "Washington",
		"administrative_area" : "DC",
		"postal_code" : "20002",
		"geocode" : "{\"latitude\": 38.9202328, \"longitude\": -76.9999917}",
		"inserted_at" : "2020-05-22 16:18:16",
		"updated_at" : "2020-05-22 16:18:16"
	},
	{
		"id" : 341,
		"unit_id" : 2613,
		"thoroughfare" : "410 Rhode Island Ave NE",
		"locality" : "Washington",
		"administrative_area" : "DC",
		"postal_code" : "20002",
		"geocode" : "{\"latitude\": 38.9202328, \"longitude\": -76.9999917}",
		"inserted_at" : "2020-05-22 16:19:00",
		"updated_at" : "2020-05-22 16:19:00"
	},
	{
		"id" : 342,
		"unit_id" : 2624,
		"thoroughfare" : "410 Rhode Island Ave NE",
		"locality" : "Washington",
		"administrative_area" : "DC",
		"postal_code" : "20002",
		"geocode" : "{\"latitude\": 38.9202328, \"longitude\": -76.9999917}",
		"inserted_at" : "2020-05-22 16:19:39",
		"updated_at" : "2020-05-22 16:19:39"
	},
	{
		"id" : 343,
		"unit_id" : 2585,
		"thoroughfare" : "410 Rhode Island Ave NE",
		"locality" : "Washington",
		"administrative_area" : "DC",
		"postal_code" : "20002",
		"geocode" : "{\"latitude\": 38.9202328, \"longitude\": -76.9999917}",
		"inserted_at" : "2020-05-22 16:20:22",
		"updated_at" : "2020-05-22 16:20:22"
	},
	{
		"id" : 345,
		"unit_id" : 2593,
		"thoroughfare" : "410 Rhode Island Ave NE",
		"locality" : "Washington",
		"administrative_area" : "DC",
		"postal_code" : "20002",
		"geocode" : "{\"latitude\": 38.9202328, \"longitude\": -76.9999917}",
		"inserted_at" : "2020-05-22 16:21:43",
		"updated_at" : "2020-05-22 16:21:43"
	},
	{
		"id" : 346,
		"unit_id" : 2598,
		"thoroughfare" : "410 Rhode Island Ave NE",
		"locality" : "Washington",
		"administrative_area" : "DC",
		"postal_code" : "20002",
		"geocode" : "{\"latitude\": 38.9202328, \"longitude\": -76.9999917}",
		"inserted_at" : "2020-05-22 16:22:10",
		"updated_at" : "2020-05-22 16:22:10"
	},
	{
		"id" : 347,
		"unit_id" : 2621,
		"thoroughfare" : "410 Rhode Island Ave NE",
		"locality" : "Washington",
		"administrative_area" : "DC",
		"postal_code" : "20002",
		"geocode" : "{\"latitude\": 38.9202328, \"longitude\": -76.9999917}",
		"inserted_at" : "2020-05-22 16:22:44",
		"updated_at" : "2020-05-22 16:22:44"
	},
	{
		"id" : 348,
		"unit_id" : 2616,
		"thoroughfare" : "410 Rhode Island Ave NE",
		"locality" : "Washington",
		"administrative_area" : "DC",
		"postal_code" : "20002",
		"geocode" : "{\"latitude\": 38.9202328, \"longitude\": -76.9999917}",
		"inserted_at" : "2020-05-22 16:23:19",
		"updated_at" : "2020-05-22 16:23:19"
	},
	{
		"id" : 349,
		"unit_id" : 2574,
		"thoroughfare" : "410 Rhode Island Ave NE",
		"locality" : "Washington",
		"administrative_area" : "DC",
		"postal_code" : "20002",
		"geocode" : "{\"latitude\": 38.9202328, \"longitude\": -76.9999917}",
		"inserted_at" : "2020-05-22 16:24:02",
		"updated_at" : "2020-05-22 16:24:02"
	},
	{
		"id" : 350,
		"unit_id" : 2629,
		"thoroughfare" : "410 Rhode Island Ave NE",
		"locality" : "Washington",
		"administrative_area" : "DC",
		"postal_code" : "20002",
		"geocode" : "{\"latitude\": 38.9202328, \"longitude\": -76.9999917}",
		"inserted_at" : "2020-05-22 16:24:34",
		"updated_at" : "2020-05-22 16:24:34"
	},
	{
		"id" : 351,
		"unit_id" : 2603,
		"thoroughfare" : "410 Rhode Island Ave NE",
		"locality" : "Washington",
		"administrative_area" : "DC",
		"postal_code" : "20002",
		"geocode" : "{\"latitude\": 38.9202328, \"longitude\": -76.9999917}",
		"inserted_at" : "2020-05-22 16:25:37",
		"updated_at" : "2020-05-22 16:25:37"
	},
	{
		"id" : 352,
		"unit_id" : 2608,
		"thoroughfare" : "410 Rhode Island Ave NE",
		"locality" : "Washington",
		"administrative_area" : "DC",
		"postal_code" : "20002",
		"geocode" : "{\"latitude\": 38.9202328, \"longitude\": -76.9999917}",
		"inserted_at" : "2020-05-22 16:26:02",
		"updated_at" : "2020-05-22 16:26:02"
	},
	{
		"id" : 353,
		"unit_id" : 2578,
		"thoroughfare" : "410 Rhode Island Ave NE",
		"locality" : "Washington",
		"administrative_area" : "DC",
		"postal_code" : "20002",
		"geocode" : "{\"latitude\": 38.9202328, \"longitude\": -76.9999917}",
		"inserted_at" : "2020-05-22 16:27:20",
		"updated_at" : "2020-05-22 16:27:20"
	},
	{
		"id" : 354,
		"unit_id" : 2638,
		"thoroughfare" : "410 Rhode Island Ave NE",
		"locality" : "Washington",
		"administrative_area" : "DC",
		"postal_code" : "20002",
		"geocode" : "{\"latitude\": 38.9202328, \"longitude\": -76.9999917}",
		"inserted_at" : "2020-05-22 16:28:04",
		"updated_at" : "2020-05-22 16:28:04"
	},
	{
		"id" : 356,
		"unit_id" : 2636,
		"thoroughfare" : "410 Rhode Island Ave NE",
		"locality" : "Washington",
		"administrative_area" : "DC",
		"postal_code" : "20002",
		"geocode" : "{\"latitude\": 38.9202328, \"longitude\": -76.9999917}",
		"inserted_at" : "2020-05-22 16:29:11",
		"updated_at" : "2020-05-22 16:29:11"
	},
	{
		"id" : 357,
		"unit_id" : 2637,
		"thoroughfare" : "410 Rhode Island Ave NE",
		"locality" : "Washington",
		"administrative_area" : "DC",
		"postal_code" : "20002",
		"geocode" : "{\"latitude\": 38.9202328, \"longitude\": -76.9999917}",
		"inserted_at" : "2020-05-22 16:29:40",
		"updated_at" : "2020-05-22 16:29:40"
	},
	{
		"id" : 358,
		"unit_id" : 2575,
		"thoroughfare" : "410 Rhode Island Ave NE",
		"locality" : "Washington",
		"administrative_area" : "DC",
		"postal_code" : "20002",
		"geocode" : "{\"latitude\": 38.9202328, \"longitude\": -76.9999917}",
		"inserted_at" : "2020-05-22 16:34:06",
		"updated_at" : "2020-05-22 16:34:06"
	},
	{
		"id" : 359,
		"unit_id" : 2588,
		"thoroughfare" : "410 Rhode Island Ave NE",
		"locality" : "Washington",
		"administrative_area" : "DC",
		"postal_code" : "20002",
		"geocode" : "{\"latitude\": 38.9202328, \"longitude\": -76.9999917}",
		"inserted_at" : "2020-05-22 16:43:07",
		"updated_at" : "2020-05-22 16:43:07"
	},
	{
		"id" : 360,
		"unit_id" : 2634,
		"thoroughfare" : "410 Rhode Island Ave NE",
		"locality" : "Washington",
		"administrative_area" : "DC",
		"postal_code" : "20002",
		"geocode" : "{\"latitude\": 38.9202328, \"longitude\": -76.9999917}",
		"inserted_at" : "2020-05-22 17:09:36",
		"updated_at" : "2020-05-22 17:09:36"
	},
	{
		"id" : 363,
		"unit_id" : 2635,
		"thoroughfare" : "410 Rhode Island Ave NE",
		"locality" : "Washington",
		"administrative_area" : "DC",
		"postal_code" : "20002",
		"geocode" : "{\"latitude\": 38.9202328, \"longitude\": -76.9999917}",
		"inserted_at" : "2020-05-22 17:14:12",
		"updated_at" : "2020-05-22 17:14:12"
	},
	{
		"id" : 364,
		"unit_id" : 2260,
		"thoroughfare" : "2124 Arizona St",
		"locality" : "Philadelphia",
		"administrative_area" : "PA",
		"postal_code" : "19125",
		"geocode" : "{\"latitude\": 39.9815985, \"longitude\": -75.1286846}",
		"inserted_at" : "2020-05-23 00:13:45",
		"updated_at" : "2020-05-23 00:13:45"
	},
	{
		"id" : 365,
		"unit_id" : 2261,
		"thoroughfare" : "2124 Arizona St",
		"locality" : "Philadelphia",
		"administrative_area" : "PA",
		"postal_code" : "19125",
		"geocode" : "{\"latitude\": 39.9815985, \"longitude\": -75.1286846}",
		"inserted_at" : "2020-05-23 00:13:59",
		"updated_at" : "2020-05-23 00:13:59"
	},
	{
		"id" : 366,
		"unit_id" : 2262,
		"thoroughfare" : "2125 E Dakota St ",
		"locality" : "Philadelphia",
		"administrative_area" : "PA",
		"postal_code" : "19125",
		"geocode" : "{\"latitude\": 39.9815634, \"longitude\": -75.128749}",
		"inserted_at" : "2020-05-23 00:14:11",
		"updated_at" : "2020-05-23 00:14:11"
	},
	{
		"id" : 367,
		"unit_id" : 2263,
		"thoroughfare" : "2125 E Dakota St",
		"locality" : "Philadelphia",
		"administrative_area" : "PA",
		"postal_code" : "19125",
		"geocode" : "{\"latitude\": 39.9815634, \"longitude\": -75.128749}",
		"inserted_at" : "2020-05-23 00:14:25",
		"updated_at" : "2020-05-23 00:14:25"
	},
	{
		"id" : 368,
		"unit_id" : 2264,
		"thoroughfare" : "2126 Arizona St",
		"locality" : "Philadelphia",
		"administrative_area" : "PA",
		"postal_code" : "19125",
		"geocode" : "{\"latitude\": 39.9815876, \"longitude\": -75.1285819}",
		"inserted_at" : "2020-05-23 00:14:39",
		"updated_at" : "2020-05-23 00:14:39"
	},
	{
		"id" : 369,
		"unit_id" : 2265,
		"thoroughfare" : "2126 Arizona St",
		"locality" : "Philadelphia",
		"administrative_area" : "PA",
		"postal_code" : "19125",
		"geocode" : "{\"latitude\": 39.9815876, \"longitude\": -75.1285819}",
		"inserted_at" : "2020-05-23 00:14:57",
		"updated_at" : "2020-05-23 00:14:57"
	},
	{
		"id" : 370,
		"unit_id" : 2644,
		"thoroughfare" : "965 N Lawrence",
		"locality" : "Philadelphia",
		"administrative_area" : "PA",
		"postal_code" : "19123",
		"geocode" : "{\"latitude\": 39.96766059999999, \"longitude\": -75.14439109999999}",
		"inserted_at" : "2020-05-27 13:02:59",
		"updated_at" : "2020-05-27 13:02:59"
	},
	{
		"id" : 375,
		"unit_id" : 2649,
		"thoroughfare" : "3100 N Ocean Drive",
		"locality" : "Singer Island-Riviera Beach",
		"administrative_area" : "FL",
		"postal_code" : "33404",
		"geocode" : "{\"latitude\": 26.7880657, \"longitude\": -80.034346}",
		"inserted_at" : "2020-06-05 20:42:50",
		"updated_at" : "2020-06-05 20:42:50"
	},
	{
		"id" : 376,
		"unit_id" : 2651,
		"thoroughfare" : "3100 N Ocean Drive",
		"locality" : "Singer Island-Riviera Beach",
		"administrative_area" : "FL",
		"postal_code" : "33404",
		"geocode" : "{\"latitude\": 26.7880657, \"longitude\": -80.034346}",
		"inserted_at" : "2020-06-05 20:43:57",
		"updated_at" : "2020-06-05 20:43:57"
	},
	{
		"id" : 377,
		"unit_id" : 2458,
		"thoroughfare" : "574 Boulevard Place NE, Unit 3",
		"locality" : "Atlanta",
		"administrative_area" : "GA",
		"postal_code" : "30308",
		"geocode" : "{\"latitude\": 33.7699167, \"longitude\": -84.36833349999999}",
		"inserted_at" : "2020-06-12 13:41:04",
		"updated_at" : "2020-06-12 13:41:04"
	},
	{
		"id" : 482,
		"unit_id" : 2897,
		"thoroughfare" : "2110 Honey Lane",
		"locality" : "Celina",
		"administrative_area" : "TX",
		"postal_code" : "75009",
		"geocode" : "{\"latitude\": 33.3251719, \"longitude\": -96.6865031}",
		"inserted_at" : "2020-07-23 17:46:33",
		"updated_at" : "2020-07-23 17:46:33"
	},
	{
		"id" : 485,
		"unit_id" : 2567,
		"thoroughfare" : "81 Thompson St, unit 301",
		"locality" : "Alpharetta",
		"administrative_area" : "GA",
		"postal_code" : "30009",
		"geocode" : "{\"latitude\": 34.071826, \"longitude\": -84.2909947}",
		"inserted_at" : "2020-07-26 19:47:11",
		"updated_at" : "2020-07-26 19:47:11"
	},
	{
		"id" : 538,
		"unit_id" : 2545,
		"thoroughfare" : "270 Southerland Terrace",
		"locality" : "Atlanta ",
		"administrative_area" : "GA",
		"postal_code" : "30307",
		"geocode" : "{\"latitude\": 33.7613649, \"longitude\": -84.3247138}",
		"inserted_at" : "2020-08-28 17:12:17",
		"updated_at" : "2020-08-28 17:12:17"
	},
	{
		"id" : 555,
		"unit_id" : 2609,
		"thoroughfare" : "410 Rhode Island Ave NE",
		"locality" : "Washington",
		"administrative_area" : "DC",
		"postal_code" : "20002",
		"geocode" : "{\"latitude\": 38.9202328, \"longitude\": -76.9999917}",
		"inserted_at" : "2020-09-03 17:39:20",
		"updated_at" : "2020-09-03 17:39:20"
	},
	{
		"id" : 556,
		"unit_id" : 2361,
		"thoroughfare" : "775 Juniper Street, #320",
		"locality" : "Atlanta",
		"administrative_area" : "Georgia",
		"postal_code" : "30308",
		"geocode" : "{\"latitude\": 33.7754039, \"longitude\": -84.3826139}",
		"inserted_at" : "2020-09-09 19:12:38",
		"updated_at" : "2020-09-09 19:12:38"
	},
	{
		"id" : 563,
		"unit_id" : 2809,
		"thoroughfare" : "425 Liberty Star Road",
		"locality" : "Wendell",
		"administrative_area" : "NC",
		"postal_code" : "27591",
		"geocode" : "{\"latitude\": 35.7680508, \"longitude\": -78.4323369}",
		"inserted_at" : "2020-09-28 17:34:47",
		"updated_at" : "2020-09-28 17:34:47"
	},
	{
		"id" : 565,
		"unit_id" : 2463,
		"thoroughfare" : "6896 Peachtree Dunwoody Road",
		"locality" : "Sandy Springs",
		"administrative_area" : "GA",
		"postal_code" : "30328",
		"geocode" : "{\"latitude\": 33.9432788, \"longitude\": -84.3526189}",
		"inserted_at" : "2020-10-14 19:25:52",
		"updated_at" : "2020-10-14 19:25:52"
	},
	{
		"id" : 572,
		"unit_id" : 2526,
		"thoroughfare" : "6892 Peachtree Dunwoody Road",
		"locality" : "Sandy Springs",
		"administrative_area" : "GA",
		"postal_code" : "30328",
		"geocode" : "{\"latitude\": 33.9432634, \"longitude\": -84.3526207}",
		"inserted_at" : "2020-10-14 19:27:43",
		"updated_at" : "2020-10-14 19:27:43"
	},
	{
		"id" : 573,
		"unit_id" : 2464,
		"thoroughfare" : "6908 Peachtree Dunwoody Road",
		"locality" : "Sandy Springs",
		"administrative_area" : "GA",
		"postal_code" : "30328",
		"geocode" : "{\"latitude\": 33.9433247, \"longitude\": -84.3526133}",
		"inserted_at" : "2020-10-14 19:27:59",
		"updated_at" : "2020-10-14 19:27:59"
	},
	{
		"id" : 580,
		"unit_id" : 2521,
		"thoroughfare" : "6899 Peachtree Dunwoody Road",
		"locality" : "Sandy Springs",
		"administrative_area" : "GA",
		"postal_code" : "30328",
		"geocode" : "{\"latitude\": 33.9446739, \"longitude\": -84.3530056}",
		"inserted_at" : "2020-10-14 19:29:56",
		"updated_at" : "2020-10-14 19:29:56"
	},
	{
		"id" : 581,
		"unit_id" : 2527,
		"thoroughfare" : "6894 Peachtree Dunwoody Road",
		"locality" : "Sandy Springs",
		"administrative_area" : "GA",
		"postal_code" : "30328",
		"geocode" : "{\"latitude\": 33.9432711, \"longitude\": -84.3526198}",
		"inserted_at" : "2020-10-14 19:30:12",
		"updated_at" : "2020-10-14 19:30:12"
	},
	{
		"id" : 582,
		"unit_id" : 2534,
		"thoroughfare" : "6890 Peachtree Dunwoody Road",
		"locality" : "Sandy Springs",
		"administrative_area" : "GA",
		"postal_code" : "30328",
		"geocode" : "{\"latitude\": 33.9432558, \"longitude\": -84.3526219}",
		"inserted_at" : "2020-10-14 19:30:29",
		"updated_at" : "2020-10-14 19:30:29"
	},
	{
		"id" : 602,
		"unit_id" : 1053,
		"thoroughfare" : "22 Airline Street, Unit # 101",
		"locality" : "Atlanta",
		"administrative_area" : "GA",
		"postal_code" : "30312",
		"geocode" : "{\"latitude\": 33.7561763, \"longitude\": -84.36709379999999}",
		"inserted_at" : "2021-01-28 20:50:41",
		"updated_at" : "2021-01-28 20:50:41"
	},
	{
		"id" : 603,
		"unit_id" : 2832,
		"thoroughfare" : "376 Bennett Mountain Trace",
		"locality" : "Chapel Hill",
		"administrative_area" : "NC",
		"postal_code" : "27516",
		"geocode" : "{\"latitude\": 35.8290808, \"longitude\": -79.100822}",
		"inserted_at" : "2021-03-15 17:26:01",
		"updated_at" : "2021-03-15 17:26:01"
	},
	{
		"id" : 605,
		"unit_id" : 2828,
		"thoroughfare" : "1416 Reservoir View",
		"locality" : "Wake Forest",
		"administrative_area" : "NC",
		"postal_code" : "27587",
		"geocode" : "{\"latitude\": 35.9786659, \"longitude\": -78.4850565}",
		"inserted_at" : "2021-03-15 17:37:43",
		"updated_at" : "2021-03-15 17:37:43"
	},
	{
		"id" : 607,
		"unit_id" : 2522,
		"thoroughfare" : "6891 Peachtree Dunwoody Road",
		"locality" : "Sandy Springs",
		"administrative_area" : "GA",
		"postal_code" : "30328",
		"geocode" : "{\"latitude\": 33.9443256, \"longitude\": -84.3520155}",
		"inserted_at" : "2021-03-26 14:57:01",
		"updated_at" : "2021-03-26 14:57:01"
	},
	{
		"id" : 608,
		"unit_id" : 2531,
		"thoroughfare" : "6904 Peachtree Dunwoody Road",
		"locality" : "Sandy Springs",
		"administrative_area" : "GA",
		"postal_code" : "30328",
		"geocode" : "{\"latitude\": 33.9433094, \"longitude\": -84.3526152}",
		"inserted_at" : "2021-03-26 14:57:31",
		"updated_at" : "2021-03-26 14:57:31"
	},
	{
		"id" : 609,
		"unit_id" : 2465,
		"thoroughfare" : "6902 Peachtree Dunwoody Road",
		"locality" : "Sandy Springs",
		"administrative_area" : "GA",
		"postal_code" : "30328",
		"geocode" : "{\"latitude\": 33.9433017, \"longitude\": -84.35261609999999}",
		"inserted_at" : "2021-03-26 14:57:56",
		"updated_at" : "2021-03-26 14:57:56"
	},
	{
		"id" : 610,
		"unit_id" : 2533,
		"thoroughfare" : "6907 Peachtree Dunwoody Road",
		"locality" : "Sandy Springs",
		"administrative_area" : "GA",
		"postal_code" : "30328",
		"geocode" : "{\"latitude\": 33.945649, \"longitude\": -84.3525628}",
		"inserted_at" : "2021-03-26 14:58:17",
		"updated_at" : "2021-03-26 14:58:17"
	},
	{
		"id" : 611,
		"unit_id" : 2523,
		"thoroughfare" : "6900 Peachtree Dunwoody Road",
		"locality" : "Sandy Springs",
		"administrative_area" : "GA",
		"postal_code" : "30328",
		"geocode" : "{\"latitude\": 33.9432941, \"longitude\": -84.352617}",
		"inserted_at" : "2021-03-26 14:58:37",
		"updated_at" : "2021-03-26 14:58:37"
	},
	{
		"id" : 612,
		"unit_id" : 2520,
		"thoroughfare" : "6897 Peachtree Dunwoody Road",
		"locality" : "Sandy Springs",
		"administrative_area" : "GA",
		"postal_code" : "30328",
		"geocode" : "{\"latitude\": 33.944595, \"longitude\": -84.3529375}",
		"inserted_at" : "2021-03-26 14:59:02",
		"updated_at" : "2021-03-26 14:59:02"
	},
	{
		"id" : 613,
		"unit_id" : 2529,
		"thoroughfare" : "6905 Peachtree Dunwoody Road",
		"locality" : "Sandy Springs",
		"administrative_area" : "GA",
		"postal_code" : "30328",
		"geocode" : "{\"latitude\": 33.9449693, \"longitude\": -84.35328299999999}",
		"inserted_at" : "2021-03-26 14:59:22",
		"updated_at" : "2021-03-26 14:59:22"
	},
	{
		"id" : 614,
		"unit_id" : 2524,
		"thoroughfare" : "6901 Peachtree Dunwoody Road",
		"locality" : "Sandy Springs",
		"administrative_area" : "GA",
		"postal_code" : "30328",
		"geocode" : "{\"latitude\": 33.9447528, \"longitude\": -84.3530737}",
		"inserted_at" : "2021-03-26 14:59:46",
		"updated_at" : "2021-03-26 14:59:46"
	},
	{
		"id" : 615,
		"unit_id" : 2462,
		"thoroughfare" : "6898 Peachtree Dunwoody Road",
		"locality" : "Sandy Springs",
		"administrative_area" : "GA",
		"postal_code" : "30328",
		"geocode" : "{\"latitude\": 33.9432864, \"longitude\": -84.3526179}",
		"inserted_at" : "2021-03-26 15:00:13",
		"updated_at" : "2021-03-26 15:00:13"
	},
	{
		"id" : 616,
		"unit_id" : 2530,
		"thoroughfare" : "6906 Peachtree Dunwoody Road",
		"locality" : "Sandy Springs",
		"administrative_area" : "GA",
		"postal_code" : "30328",
		"geocode" : "{\"latitude\": 33.9433171, \"longitude\": -84.35261419999999}",
		"inserted_at" : "2021-03-26 15:00:34",
		"updated_at" : "2021-03-26 15:00:34"
	},
	{
		"id" : 617,
		"unit_id" : 2528,
		"thoroughfare" : "6903 Peachtree Dunwoody Road",
		"locality" : "Sandy Springs",
		"administrative_area" : "GA",
		"postal_code" : "30328",
		"geocode" : "{\"latitude\": 33.9448352, \"longitude\": -84.35296369999999}",
		"inserted_at" : "2021-03-26 15:00:54",
		"updated_at" : "2021-03-26 15:00:54"
	},
	{
		"id" : 622,
		"unit_id" : 2849,
		"thoroughfare" : "675 Drewry Street",
		"locality" : "Atlanta",
		"administrative_area" : "GA",
		"postal_code" : "30306",
		"geocode" : "{\"latitude\": 33.7774957, \"longitude\": -84.36517169999999}",
		"inserted_at" : "2021-03-27 18:41:06",
		"updated_at" : "2021-03-27 18:41:06"
	},
	{
		"id" : 623,
		"unit_id" : 2850,
		"thoroughfare" : "675 Drewry Street",
		"locality" : "Atlanta",
		"administrative_area" : "GA",
		"postal_code" : "30306",
		"geocode" : "{\"latitude\": 33.7774957, \"longitude\": -84.36517169999999}",
		"inserted_at" : "2021-03-27 18:41:26",
		"updated_at" : "2021-03-27 18:41:26"
	},
	{
		"id" : 624,
		"unit_id" : 2851,
		"thoroughfare" : "675 Drewry Street",
		"locality" : "Atlanta",
		"administrative_area" : "GA",
		"postal_code" : "30306",
		"geocode" : "{\"latitude\": 33.7774957, \"longitude\": -84.36517169999999}",
		"inserted_at" : "2021-03-27 18:41:40",
		"updated_at" : "2021-03-27 18:41:40"
	},
	{
		"id" : 625,
		"unit_id" : 2852,
		"thoroughfare" : "675 Drewry Street",
		"locality" : "Atlanta",
		"administrative_area" : "GA",
		"postal_code" : "30306",
		"geocode" : "{\"latitude\": 33.7774957, \"longitude\": -84.36517169999999}",
		"inserted_at" : "2021-03-27 18:41:55",
		"updated_at" : "2021-03-27 18:41:55"
	},
	{
		"id" : 626,
		"unit_id" : 2853,
		"thoroughfare" : "675 Drewry Street",
		"locality" : "Atlanta",
		"administrative_area" : "GA",
		"postal_code" : "30306",
		"geocode" : "{\"latitude\": 33.7774957, \"longitude\": -84.36517169999999}",
		"inserted_at" : "2021-03-27 18:42:12",
		"updated_at" : "2021-03-27 18:42:12"
	},
	{
		"id" : 627,
		"unit_id" : 2854,
		"thoroughfare" : "675 Drewry Street",
		"locality" : "Atlanta",
		"administrative_area" : "GA",
		"postal_code" : "30306",
		"geocode" : "{\"latitude\": 33.7774957, \"longitude\": -84.36517169999999}",
		"inserted_at" : "2021-03-27 18:42:34",
		"updated_at" : "2021-03-27 18:42:34"
	},
	{
		"id" : 628,
		"unit_id" : 2855,
		"thoroughfare" : "675 Drewry Street",
		"locality" : "Atlanta",
		"administrative_area" : "GA",
		"postal_code" : "30306",
		"geocode" : "{\"latitude\": 33.7774957, \"longitude\": -84.36517169999999}",
		"inserted_at" : "2021-03-27 18:42:47",
		"updated_at" : "2021-03-27 18:42:47"
	},
	{
		"id" : 629,
		"unit_id" : 2856,
		"thoroughfare" : "675 Drewry Street",
		"locality" : "Atlanta",
		"administrative_area" : "GA",
		"postal_code" : "30306",
		"geocode" : "{\"latitude\": 33.7774957, \"longitude\": -84.36517169999999}",
		"inserted_at" : "2021-03-27 18:43:04",
		"updated_at" : "2021-03-27 18:43:04"
	},
	{
		"id" : 630,
		"unit_id" : 2857,
		"thoroughfare" : "675 Drewry Street",
		"locality" : "Atlanta",
		"administrative_area" : "GA",
		"postal_code" : "30306",
		"geocode" : "{\"latitude\": 33.7774957, \"longitude\": -84.36517169999999}",
		"inserted_at" : "2021-03-27 18:43:20",
		"updated_at" : "2021-03-27 18:43:20"
	},
	{
		"id" : 631,
		"unit_id" : 2858,
		"thoroughfare" : "675 Drewry Street",
		"locality" : "Atlanta",
		"administrative_area" : "GA",
		"postal_code" : "30306",
		"geocode" : "{\"latitude\": 33.7774957, \"longitude\": -84.36517169999999}",
		"inserted_at" : "2021-03-27 18:43:36",
		"updated_at" : "2021-03-27 18:43:36"
	},
	{
		"id" : 632,
		"unit_id" : 2859,
		"thoroughfare" : "675 Drewry Street",
		"locality" : "Atlanta",
		"administrative_area" : "GA",
		"postal_code" : "30306",
		"geocode" : "{\"latitude\": 33.7774957, \"longitude\": -84.36517169999999}",
		"inserted_at" : "2021-03-27 18:43:49",
		"updated_at" : "2021-03-27 18:43:49"
	},
	{
		"id" : 633,
		"unit_id" : 2860,
		"thoroughfare" : "675 Drewry Street",
		"locality" : "Atlanta",
		"administrative_area" : "GA",
		"postal_code" : "30306",
		"geocode" : "{\"latitude\": 33.7774957, \"longitude\": -84.36517169999999}",
		"inserted_at" : "2021-03-27 18:44:03",
		"updated_at" : "2021-03-27 18:44:03"
	},
	{
		"id" : 634,
		"unit_id" : 2861,
		"thoroughfare" : "675 Drewry Street",
		"locality" : "Atlanta",
		"administrative_area" : "GA",
		"postal_code" : "30306",
		"geocode" : "{\"latitude\": 33.7774957, \"longitude\": -84.36517169999999}",
		"inserted_at" : "2021-03-27 18:44:15",
		"updated_at" : "2021-03-27 18:44:15"
	},
	{
		"id" : 635,
		"unit_id" : 2863,
		"thoroughfare" : "675 Drewry Street",
		"locality" : "Atlanta",
		"administrative_area" : "GA",
		"postal_code" : "30306",
		"geocode" : "{\"latitude\": 33.7774957, \"longitude\": -84.36517169999999}",
		"inserted_at" : "2021-03-27 18:44:36",
		"updated_at" : "2021-03-27 18:44:36"
	},
	{
		"id" : 638,
		"unit_id" : 2866,
		"thoroughfare" : "675 Drewry Street",
		"locality" : "Atlanta",
		"administrative_area" : "GA",
		"postal_code" : "30306",
		"geocode" : "{\"latitude\": 33.7774957, \"longitude\": -84.36517169999999}",
		"inserted_at" : "2021-03-27 18:45:22",
		"updated_at" : "2021-03-27 18:45:22"
	},
	{
		"id" : 639,
		"unit_id" : 2867,
		"thoroughfare" : "675 Drewry Street",
		"locality" : "Atlanta",
		"administrative_area" : "GA",
		"postal_code" : "30306",
		"geocode" : "{\"latitude\": 33.7774957, \"longitude\": -84.36517169999999}",
		"inserted_at" : "2021-03-27 18:45:35",
		"updated_at" : "2021-03-27 18:45:35"
	},
	{
		"id" : 640,
		"unit_id" : 2868,
		"thoroughfare" : "675 Drewry Street",
		"locality" : "Atlanta",
		"administrative_area" : "GA",
		"postal_code" : "30306",
		"geocode" : "{\"latitude\": 33.7774957, \"longitude\": -84.36517169999999}",
		"inserted_at" : "2021-03-27 18:45:47",
		"updated_at" : "2021-03-27 18:45:47"
	},
	{
		"id" : 641,
		"unit_id" : 2869,
		"thoroughfare" : "675 Drewry Street",
		"locality" : "Atlanta",
		"administrative_area" : "GA",
		"postal_code" : "30306",
		"geocode" : "{\"latitude\": 33.7774957, \"longitude\": -84.36517169999999}",
		"inserted_at" : "2021-03-27 18:45:59",
		"updated_at" : "2021-03-27 18:45:59"
	},
	{
		"id" : 642,
		"unit_id" : 2870,
		"thoroughfare" : "675 Drewry Street",
		"locality" : "Atlanta",
		"administrative_area" : "GA",
		"postal_code" : "30306",
		"geocode" : "{\"latitude\": 33.7774957, \"longitude\": -84.36517169999999}",
		"inserted_at" : "2021-03-27 18:46:15",
		"updated_at" : "2021-03-27 18:46:15"
	},
	{
		"id" : 643,
		"unit_id" : 2871,
		"thoroughfare" : "675 Drewry Street",
		"locality" : "Atlanta",
		"administrative_area" : "GA",
		"postal_code" : "30306",
		"geocode" : "{\"latitude\": 33.7774957, \"longitude\": -84.36517169999999}",
		"inserted_at" : "2021-03-27 18:46:30",
		"updated_at" : "2021-03-27 18:46:30"
	},
	{
		"id" : 644,
		"unit_id" : 2872,
		"thoroughfare" : "675 Drewry Street",
		"locality" : "Atlanta",
		"administrative_area" : "GA",
		"postal_code" : "30306",
		"geocode" : "{\"latitude\": 33.7774957, \"longitude\": -84.36517169999999}",
		"inserted_at" : "2021-03-27 18:46:45",
		"updated_at" : "2021-03-27 18:46:45"
	},
	{
		"id" : 645,
		"unit_id" : 2873,
		"thoroughfare" : "675 Drewry Street",
		"locality" : "Atlanta",
		"administrative_area" : "GA",
		"postal_code" : "30306",
		"geocode" : "{\"latitude\": 33.7774957, \"longitude\": -84.36517169999999}",
		"inserted_at" : "2021-03-27 18:47:03",
		"updated_at" : "2021-03-27 18:47:03"
	},
	{
		"id" : 646,
		"unit_id" : 2874,
		"thoroughfare" : "675 Drewry Street",
		"locality" : "Atlanta",
		"administrative_area" : "GA",
		"postal_code" : "30306",
		"geocode" : "{\"latitude\": 33.7774957, \"longitude\": -84.36517169999999}",
		"inserted_at" : "2021-03-27 18:47:22",
		"updated_at" : "2021-03-27 18:47:22"
	},
	{
		"id" : 647,
		"unit_id" : 2875,
		"thoroughfare" : "675 Drewry Street",
		"locality" : "Atlanta",
		"administrative_area" : "GA",
		"postal_code" : "30306",
		"geocode" : "{\"latitude\": 33.7774957, \"longitude\": -84.36517169999999}",
		"inserted_at" : "2021-03-27 18:47:36",
		"updated_at" : "2021-03-27 18:47:36"
	},
	{
		"id" : 648,
		"unit_id" : 2876,
		"thoroughfare" : "675 Drewry Street",
		"locality" : "Atlanta",
		"administrative_area" : "GA",
		"postal_code" : "30306",
		"geocode" : "{\"latitude\": 33.7774957, \"longitude\": -84.36517169999999}",
		"inserted_at" : "2021-03-27 18:47:51",
		"updated_at" : "2021-03-27 18:47:51"
	},
	{
		"id" : 649,
		"unit_id" : 2877,
		"thoroughfare" : "675 Drewry Street",
		"locality" : "Atlanta",
		"administrative_area" : "GA",
		"postal_code" : "30306",
		"geocode" : "{\"latitude\": 33.7774957, \"longitude\": -84.36517169999999}",
		"inserted_at" : "2021-03-27 18:48:05",
		"updated_at" : "2021-03-27 18:48:05"
	},
	{
		"id" : 651,
		"unit_id" : 2878,
		"thoroughfare" : "675 Drewry Street",
		"locality" : "Atlanta",
		"administrative_area" : "GA",
		"postal_code" : "30306",
		"geocode" : "{\"latitude\": 33.7774957, \"longitude\": -84.36517169999999}",
		"inserted_at" : "2021-03-27 18:48:36",
		"updated_at" : "2021-03-27 18:48:36"
	},
	{
		"id" : 652,
		"unit_id" : 2879,
		"thoroughfare" : "675 Drewry Street",
		"locality" : "Atlanta",
		"administrative_area" : "GA",
		"postal_code" : "30306",
		"geocode" : "{\"latitude\": 33.7774957, \"longitude\": -84.36517169999999}",
		"inserted_at" : "2021-03-27 18:48:47",
		"updated_at" : "2021-03-27 18:48:47"
	},
	{
		"id" : 653,
		"unit_id" : 2880,
		"thoroughfare" : "675 Drewry Street",
		"locality" : "Atlanta",
		"administrative_area" : "GA",
		"postal_code" : "30306",
		"geocode" : "{\"latitude\": 33.7774957, \"longitude\": -84.36517169999999}",
		"inserted_at" : "2021-03-27 18:49:01",
		"updated_at" : "2021-03-27 18:49:01"
	},
	{
		"id" : 654,
		"unit_id" : 2881,
		"thoroughfare" : "675 Drewry Street",
		"locality" : "Atlanta",
		"administrative_area" : "GA",
		"postal_code" : "30306",
		"geocode" : "{\"latitude\": 33.7774957, \"longitude\": -84.36517169999999}",
		"inserted_at" : "2021-03-27 18:49:19",
		"updated_at" : "2021-03-27 18:49:19"
	},
	{
		"id" : 657,
		"unit_id" : 2884,
		"thoroughfare" : "675 Drewry Street",
		"locality" : "Atlanta",
		"administrative_area" : "GA",
		"postal_code" : "30306",
		"geocode" : "{\"latitude\": 33.7774957, \"longitude\": -84.36517169999999}",
		"inserted_at" : "2021-03-27 18:50:13",
		"updated_at" : "2021-03-27 18:50:13"
	},
	{
		"id" : 658,
		"unit_id" : 2885,
		"thoroughfare" : "675 Drewry Street",
		"locality" : "Atlanta",
		"administrative_area" : "GA",
		"postal_code" : "30306",
		"geocode" : "{\"latitude\": 33.7774957, \"longitude\": -84.36517169999999}",
		"inserted_at" : "2021-03-27 18:50:27",
		"updated_at" : "2021-03-27 18:50:27"
	},
	{
		"id" : 659,
		"unit_id" : 2886,
		"thoroughfare" : "675 Drewry Street",
		"locality" : "Atlanta",
		"administrative_area" : "GA",
		"postal_code" : "30306",
		"geocode" : "{\"latitude\": 33.7774957, \"longitude\": -84.36517169999999}",
		"inserted_at" : "2021-03-27 18:50:41",
		"updated_at" : "2021-03-27 18:50:41"
	},
	{
		"id" : 660,
		"unit_id" : 2887,
		"thoroughfare" : "675 Drewry Street",
		"locality" : "Atlanta",
		"administrative_area" : "GA",
		"postal_code" : "30306",
		"geocode" : "{\"latitude\": 33.7774957, \"longitude\": -84.36517169999999}",
		"inserted_at" : "2021-03-27 18:51:01",
		"updated_at" : "2021-03-27 18:51:01"
	},
	{
		"id" : 661,
		"unit_id" : 2888,
		"thoroughfare" : "675 Drewry Street",
		"locality" : "Atlanta",
		"administrative_area" : "GA",
		"postal_code" : "30306",
		"geocode" : "{\"latitude\": 33.7774957, \"longitude\": -84.36517169999999}",
		"inserted_at" : "2021-03-27 18:51:16",
		"updated_at" : "2021-03-27 18:51:16"
	},
	{
		"id" : 663,
		"unit_id" : 2981,
		"thoroughfare" : "12444 Cortez Rd.",
		"locality" : "Cortez",
		"administrative_area" : "FL",
		"postal_code" : "34215",
		"geocode" : "{\"latitude\": 27.4693983, \"longitude\": -82.6869681}",
		"inserted_at" : "2021-04-07 20:54:37",
		"updated_at" : "2021-04-07 20:54:37"
	},
	{
		"id" : 664,
		"unit_id" : 2933,
		"thoroughfare" : "1222 Cortez road",
		"locality" : "Cortez",
		"administrative_area" : "FL",
		"postal_code" : "34215",
		"geocode" : "{\"latitude\": 27.4624647, \"longitude\": -82.5738212}",
		"inserted_at" : "2021-04-09 19:20:45",
		"updated_at" : "2021-04-09 19:20:45"
	},
	{
		"id" : 665,
		"unit_id" : 2532,
		"thoroughfare" : "6893 Peachtree Dunwoody Road",
		"locality" : "Sandy Springs",
		"administrative_area" : "GA",
		"postal_code" : "30328",
		"geocode" : "{\"latitude\": 33.9444336, \"longitude\": -84.35280759999999}",
		"inserted_at" : "2021-04-12 14:35:03",
		"updated_at" : "2021-04-12 14:35:03"
	},
	{
		"id" : 666,
		"unit_id" : 2525,
		"thoroughfare" : "6895 Peachtree Dunwoody Road",
		"locality" : "Sandy Springs",
		"administrative_area" : "GA",
		"postal_code" : "30328",
		"geocode" : "{\"latitude\": 33.9445149, \"longitude\": -84.3528716}",
		"inserted_at" : "2021-04-13 20:14:43",
		"updated_at" : "2021-04-13 20:14:43"
	},
	{
		"id" : 675,
		"unit_id" : 2837,
		"thoroughfare" : "2203 Meadowcreek Drive",
		"locality" : "Durham",
		"administrative_area" : "NC",
		"postal_code" : "27705",
		"geocode" : "{\"latitude\": 36.0584705, \"longitude\": -78.9429748}",
		"inserted_at" : "2021-06-30 19:05:45",
		"updated_at" : "2021-06-30 19:05:45"
	},
	{
		"id" : 677,
		"unit_id" : 2808,
		"thoroughfare" : "905 Celia Saxon Drive",
		"locality" : "Durham",
		"administrative_area" : "NC",
		"postal_code" : "27703",
		"geocode" : "{\"latitude\": 35.8804063, \"longitude\": -78.95714130000002}",
		"inserted_at" : "2021-06-30 19:07:06",
		"updated_at" : "2021-06-30 19:07:06"
	},
	{
		"id" : 683,
		"unit_id" : 4155,
		"thoroughfare" : "269 Tumbling River Drive",
		"locality" : "Wendell",
		"administrative_area" : "NC",
		"postal_code" : "27591",
		"geocode" : "{\"latitude\": 35.7710329, \"longitude\": -78.4228029}",
		"inserted_at" : "2021-06-30 19:20:34",
		"updated_at" : "2021-06-30 19:20:34"
	},
	{
		"id" : 686,
		"unit_id" : 4158,
		"thoroughfare" : "1012 Casa Dega Way",
		"locality" : "Raleigh",
		"administrative_area" : "NC",
		"postal_code" : "27615",
		"geocode" : "{\"latitude\": 35.8861371, \"longitude\": -78.64554749999999}",
		"inserted_at" : "2021-06-30 19:30:59",
		"updated_at" : "2021-06-30 19:30:59"
	},
	{
		"id" : 687,
		"unit_id" : 2830,
		"thoroughfare" : "2264 Duskywing Drive",
		"locality" : "Raleigh",
		"administrative_area" : "NC",
		"postal_code" : "27613",
		"geocode" : "{\"latitude\": 35.9660845, \"longitude\": -78.7145934}",
		"inserted_at" : "2021-08-02 00:10:32",
		"updated_at" : "2021-08-02 00:10:32"
	},
	{
		"id" : 688,
		"unit_id" : 4197,
		"thoroughfare" : "947 Dunleigh Meadows Ln",
		"locality" : "Houston",
		"administrative_area" : "TX",
		"postal_code" : "77024",
		"geocode" : "{\"latitude\": 29.7870421, \"longitude\": -95.4443917}",
		"inserted_at" : "2021-08-06 18:10:13",
		"updated_at" : "2021-08-06 18:10:13"
	},
	{
		"id" : 689,
		"unit_id" : 4198,
		"thoroughfare" : "951 Dunleigh Meadows Ln",
		"locality" : "Houston",
		"administrative_area" : "TX",
		"postal_code" : "77055",
		"geocode" : "{\"latitude\": 29.7870421, \"longitude\": -95.4443917}",
		"inserted_at" : "2021-08-06 20:46:57",
		"updated_at" : "2021-08-06 20:46:57"
	},
	{
		"id" : 690,
		"unit_id" : 4199,
		"thoroughfare" : "941 Dunleigh Meadows Ln",
		"locality" : "Houston",
		"administrative_area" : "TX",
		"postal_code" : "77055",
		"geocode" : "{\"latitude\": 29.7860832, \"longitude\": -95.4444083}",
		"inserted_at" : "2021-08-06 20:58:28",
		"updated_at" : "2021-08-06 20:58:28"
	},
	{
		"id" : 694,
		"unit_id" : 4202,
		"thoroughfare" : "935 Dunleigh Meadows Ln",
		"locality" : "Houston",
		"administrative_area" : "TX",
		"postal_code" : "77055",
		"geocode" : "{\"latitude\": 29.7860832, \"longitude\": -95.4444083}",
		"inserted_at" : "2021-08-15 23:30:28",
		"updated_at" : "2021-08-15 23:30:28"
	},
	{
		"id" : 695,
		"unit_id" : 4201,
		"thoroughfare" : "939 Dunleigh Meadows Ln",
		"locality" : "Houston",
		"administrative_area" : "TX",
		"postal_code" : "77055",
		"geocode" : "{\"latitude\": 29.7860832, \"longitude\": -95.4444083}",
		"inserted_at" : "2021-08-15 23:31:05",
		"updated_at" : "2021-08-15 23:31:05"
	},
	{
		"id" : 697,
		"unit_id" : 4153,
		"thoroughfare" : "2311 Timberview Drive",
		"locality" : "Durham",
		"administrative_area" : "NC",
		"postal_code" : "27705",
		"geocode" : "{\"latitude\": 36.0565715, \"longitude\": -78.9392697}",
		"inserted_at" : "2021-08-18 20:22:48",
		"updated_at" : "2021-08-18 20:22:48"
	},
	{
		"id" : 698,
		"unit_id" : 4157,
		"thoroughfare" : "1400 Blantons Creek Drive",
		"locality" : "Wake Forest",
		"administrative_area" : "NC",
		"postal_code" : "27587",
		"geocode" : "{\"latitude\": 35.9785511, \"longitude\": -78.59799290000001}",
		"inserted_at" : "2021-08-18 20:26:27",
		"updated_at" : "2021-08-18 20:26:27"
	},
	{
		"id" : 700,
		"unit_id" : 4154,
		"thoroughfare" : "807 Watercolor Way",
		"locality" : "Durham",
		"administrative_area" : "NC",
		"postal_code" : "27713",
		"geocode" : "{\"latitude\": 35.878651, \"longitude\": -78.955383}",
		"inserted_at" : "2021-08-18 20:28:43",
		"updated_at" : "2021-08-18 20:28:43"
	},
	{
		"id" : 703,
		"unit_id" : 2862,
		"thoroughfare" : "675 Drewry Street",
		"locality" : "Atlanta",
		"administrative_area" : "GA",
		"postal_code" : "30306",
		"geocode" : "{\"latitude\": 33.7774957, \"longitude\": -84.36517169999999}",
		"inserted_at" : "2021-09-15 21:33:03",
		"updated_at" : "2021-09-15 21:33:03"
	},
	{
		"id" : 704,
		"unit_id" : 4259,
		"thoroughfare" : "3305 Ridgeway Valley Lane",
		"locality" : "Houston",
		"administrative_area" : "TX",
		"postal_code" : "77055",
		"geocode" : "{\"latitude\": 29.7856145, \"longitude\": -95.4415206}",
		"inserted_at" : "2021-09-27 16:16:58",
		"updated_at" : "2021-09-27 16:16:58"
	},
	{
		"id" : 705,
		"unit_id" : 4156,
		"thoroughfare" : "1921 Stagecoach Trail",
		"locality" : "Wendell",
		"administrative_area" : "NC",
		"postal_code" : "27591",
		"geocode" : "{\"latitude\": 35.7726555, \"longitude\": -78.426638}",
		"inserted_at" : "2021-10-04 21:40:21",
		"updated_at" : "2021-10-04 21:40:21"
	},
	{
		"id" : 713,
		"unit_id" : 4293,
		"thoroughfare" : "3217 Ridgeway Valley Ln",
		"locality" : "Houston",
		"administrative_area" : "TX",
		"postal_code" : "77055",
		"geocode" : "{\"latitude\": 29.7856151, \"longitude\": -95.4415214}",
		"inserted_at" : "2021-11-06 17:39:37",
		"updated_at" : "2021-11-06 17:39:37"
	},
	{
		"id" : 715,
		"unit_id" : 4294,
		"thoroughfare" : "3303 Ridgeway Valley Ln",
		"locality" : "Houston",
		"administrative_area" : "TX",
		"postal_code" : "77055",
		"geocode" : "{\"latitude\": 29.7856151, \"longitude\": -95.4415214}",
		"inserted_at" : "2021-11-06 17:42:14",
		"updated_at" : "2021-11-06 17:42:14"
	},
	{
		"id" : 717,
		"unit_id" : 4301,
		"thoroughfare" : "3221 Ridgeway Valley Lane",
		"locality" : "Houston",
		"administrative_area" : "TX",
		"postal_code" : "77055",
		"geocode" : "{\"latitude\": 29.7856151, \"longitude\": -95.4415214}",
		"inserted_at" : "2021-12-03 01:29:53",
		"updated_at" : "2021-12-03 01:29:53"
	},
	{
		"id" : 718,
		"unit_id" : 4300,
		"thoroughfare" : "3219 Ridgeway Valley Lane",
		"locality" : "Houston",
		"administrative_area" : "TX",
		"postal_code" : "77055",
		"geocode" : "{\"latitude\": 29.7856151, \"longitude\": -95.4415214}",
		"inserted_at" : "2021-12-06 20:26:53",
		"updated_at" : "2021-12-06 20:26:53"
	},
	{
		"id" : 720,
		"unit_id" : 2883,
		"thoroughfare" : "675 Drewry Street",
		"locality" : "Atlanta",
		"administrative_area" : "GA",
		"postal_code" : "30306",
		"geocode" : "{\"latitude\": 33.7775062, \"longitude\": -84.3651818}",
		"inserted_at" : "2022-01-03 16:37:28",
		"updated_at" : "2022-01-03 16:37:28"
	},
	{
		"id" : 721,
		"unit_id" : 1060,
		"thoroughfare" : "20 Airline St NE",
		"locality" : "Atlanta",
		"administrative_area" : "GA",
		"postal_code" : "30312",
		"geocode" : "{\"latitude\": 33.7549873, \"longitude\": -84.36724679999999}",
		"inserted_at" : "2022-01-03 17:23:56",
		"updated_at" : "2022-01-03 17:23:56"
	},
	{
		"id" : 722,
		"unit_id" : 1065,
		"thoroughfare" : "20 Airline St NE",
		"locality" : "Atlanta",
		"administrative_area" : "GA",
		"postal_code" : "30312",
		"geocode" : "{\"latitude\": 33.7549873, \"longitude\": -84.36724679999999}",
		"inserted_at" : "2022-01-03 17:26:02",
		"updated_at" : "2022-01-03 17:26:02"
	},
	{
		"id" : 723,
		"unit_id" : 1066,
		"thoroughfare" : "20 Airline St NE",
		"locality" : "Atlanta",
		"administrative_area" : "GA",
		"postal_code" : "30312",
		"geocode" : "{\"latitude\": 33.7549873, \"longitude\": -84.36724679999999}",
		"inserted_at" : "2022-01-03 17:27:08",
		"updated_at" : "2022-01-03 17:27:08"
	},
	{
		"id" : 725,
		"unit_id" : 3197,
		"thoroughfare" : "5656",
		"locality" : "Houston",
		"administrative_area" : "TX",
		"postal_code" : "77056",
		"geocode" : "{\"latitude\": 29.7503996, \"longitude\": -95.4762758}",
		"inserted_at" : "2022-01-08 16:16:18",
		"updated_at" : "2022-01-08 16:16:18"
	},
	{
		"id" : 726,
		"unit_id" : 3513,
		"thoroughfare" : "lake shore dr",
		"locality" : "Palm Beach",
		"administrative_area" : "FL",
		"postal_code" : "33403",
		"geocode" : "{\"latitude\": 26.7981259, \"longitude\": -80.05341539999999}",
		"inserted_at" : "2022-01-20 16:52:55",
		"updated_at" : "2022-01-20 16:52:55"
	},
	{
		"id" : 729,
		"unit_id" : 4412,
		"thoroughfare" : "945 Dunleigh Meadows Ln",
		"locality" : "Houston",
		"administrative_area" : "TX",
		"postal_code" : "77055",
		"geocode" : "{\"latitude\": 29.7870421, \"longitude\": -95.4443938}",
		"inserted_at" : "2022-01-23 19:11:48",
		"updated_at" : "2022-01-23 19:11:48"
	},
	{
		"id" : 731,
		"unit_id" : 3056,
		"thoroughfare" : "25118 Delvin Creek",
		"locality" : "Spring",
		"administrative_area" : "Texas",
		"postal_code" : "77380",
		"geocode" : "{\"latitude\": 30.1229047, \"longitude\": -95.4748163}",
		"inserted_at" : "2022-01-25 17:22:49",
		"updated_at" : "2022-01-25 17:22:49"
	},
	{
		"id" : 732,
		"unit_id" : 4152,
		"thoroughfare" : "1354 Briar Chapel Parkway",
		"locality" : "Chapel Hill",
		"administrative_area" : "NC",
		"postal_code" : "27516",
		"geocode" : "{\"latitude\": 35.8293788, \"longitude\": -79.1023628}",
		"inserted_at" : "2022-01-27 15:30:11",
		"updated_at" : "2022-01-27 15:30:11"
	},
	{
		"id" : 733,
		"unit_id" : 4438,
		"thoroughfare" : "3721 Somerset York Ln",
		"locality" : "Houston",
		"administrative_area" : "TX",
		"postal_code" : "77055",
		"geocode" : "{\"latitude\": 29.7871758, \"longitude\": -95.4439049}",
		"inserted_at" : "2022-01-29 23:17:16",
		"updated_at" : "2022-01-29 23:17:16"
	},
	{
		"id" : 734,
		"unit_id" : 3772,
		"thoroughfare" : "Lake Shore",
		"locality" : "Lake Park",
		"administrative_area" : "FL",
		"postal_code" : "33403",
		"geocode" : "{\"latitude\": 26.7981259, \"longitude\": -80.05341539999999}",
		"inserted_at" : "2022-01-31 20:06:37",
		"updated_at" : "2022-01-31 20:06:37"
	},
	{
		"id" : 737,
		"unit_id" : 2840,
		"thoroughfare" : "675 Drewry Street",
		"locality" : "Atlanta",
		"administrative_area" : "GA",
		"postal_code" : "30306",
		"geocode" : "{\"latitude\": 33.7775062, \"longitude\": -84.3651818}",
		"inserted_at" : "2022-02-03 10:22:10",
		"updated_at" : "2022-02-03 10:22:10"
	},
	{
		"id" : 738,
		"unit_id" : 2839,
		"thoroughfare" : "675 Drewry Street",
		"locality" : "Atlanta",
		"administrative_area" : "GA",
		"postal_code" : "30306",
		"geocode" : "{\"latitude\": 33.7775062, \"longitude\": -84.3651818}",
		"inserted_at" : "2022-02-03 10:22:30",
		"updated_at" : "2022-02-03 10:22:30"
	},
	{
		"id" : 739,
		"unit_id" : 2882,
		"thoroughfare" : "675 Drewry Street",
		"locality" : "Atlanta",
		"administrative_area" : "GA",
		"postal_code" : "30306",
		"geocode" : "{\"latitude\": 33.7775062, \"longitude\": -84.3651818}",
		"inserted_at" : "2022-02-03 10:23:17",
		"updated_at" : "2022-02-03 10:23:17"
	},
	{
		"id" : 740,
		"unit_id" : 2864,
		"thoroughfare" : "675 Drewry Street",
		"locality" : "Atlanta",
		"administrative_area" : "GA",
		"postal_code" : "30306",
		"geocode" : "{\"latitude\": 33.7775062, \"longitude\": -84.3651818}",
		"inserted_at" : "2022-02-07 16:00:35",
		"updated_at" : "2022-02-07 16:00:35"
	},
	{
		"id" : 741,
		"unit_id" : 3463,
		"thoroughfare" : "220 Lake Shore",
		"locality" : "Palm Beach",
		"administrative_area" : "FL",
		"postal_code" : "33403",
		"geocode" : "{\"latitude\": 26.794158, \"longitude\": -80.05336}",
		"inserted_at" : "2022-02-10 12:19:05",
		"updated_at" : "2022-02-10 12:19:05"
	},
	{
		"id" : 742,
		"unit_id" : 2865,
		"thoroughfare" : "675 Drewry Street",
		"locality" : "Atlanta",
		"administrative_area" : "GA",
		"postal_code" : "30306",
		"geocode" : "{\"latitude\": 33.7775062, \"longitude\": -84.3651818}",
		"inserted_at" : "2022-02-16 21:00:26",
		"updated_at" : "2022-02-16 21:00:26"
	}
]
